cfour_parser/__init__.py
cfour_parser/__main__.py
cfour_parser/programs.py
cfour_parser/quadrature.py
cfour_parser/text.py
cfour_parser/util.py
cfour_parser/xdqcscf.py
cfour_parser/xjoda.py
cfour_parser/xncc.py
cfour_parser/xsim.py
cfour_parser/xvcc.py
cfour_parser/xvee.py
cfour_parser/xvscf.py
cfour_parser-0.0.3.dist-info/METADATA
cfour_parser-0.0.3.dist-info/WHEEL
cfour_parser-0.0.3.dist-info/entry_points.txt
cfour_parser-0.0.3.dist-info/top_level.txt
cfour_parser-0.0.3.dist-info/RECORD
