Metadata-Version: 2.1
Name: cfour_parser
Version: 0.0.3
Summary: Parser of the CFOUR output.
Author: Paweł Wójcik <https://github.com/the-pawel-wojcik>
License: EUROPEAN UNION PUBLIC LICENCE v. 1.2
Project-URL: repository, https://github.com/the-pawel-wojcik/cfour_parser
Keywords: CFOUR,parser
Classifier: Topic :: File Formats :: JSON
Classifier: Topic :: Scientific/Engineering :: Chemistry
Classifier: Topic :: Text Processing
Classifier: Topic :: Utilities
Requires-Dist: requests
Requires-Dist: importlib-metadata ; python_version < "3.10"
